zerodbext.catalog-0.8.4-py3.5-nspkg.pth
benchmark/__init__.py
benchmark/benchmark.py
benchmark/benchmarks.txt
benchmark/intersection.py
benchmark/sortbench.py
zerodbext/catalog/__init__.py
zerodbext/catalog/catalog.py
zerodbext/catalog/document.py
zerodbext/catalog/interfaces.py
zerodbext/catalog/migration.py
zerodbext/catalog/query.py
zerodbext/catalog/indexes/__init__.py
zerodbext/catalog/indexes/common.py
zerodbext/catalog/indexes/facet.py
zerodbext/catalog/indexes/field.py
zerodbext/catalog/indexes/keyword.py
zerodbext/catalog/indexes/path.py
zerodbext/catalog/indexes/path2.py
zerodbext/catalog/indexes/text.py
zerodbext/catalog/indexes/tests/__init__.py
zerodbext/catalog/indexes/tests/test_common.py
zerodbext/catalog/indexes/tests/test_facet.py
zerodbext/catalog/indexes/tests/test_field.py
zerodbext/catalog/indexes/tests/test_keyword.py
zerodbext/catalog/indexes/tests/test_path.py
zerodbext/catalog/indexes/tests/test_path2.py
zerodbext/catalog/indexes/tests/test_text.py
zerodbext/catalog/tests/__init__.py
zerodbext/catalog/tests/test_catalog.py
zerodbext/catalog/tests/test_document.py
zerodbext/catalog/tests/test_functional.py
zerodbext/catalog/tests/test_migration.py
zerodbext/catalog/tests/test_query.py
zerodbext.catalog-0.8.4.dist-info/DESCRIPTION.rst
zerodbext.catalog-0.8.4.dist-info/METADATA
zerodbext.catalog-0.8.4.dist-info/RECORD
zerodbext.catalog-0.8.4.dist-info/WHEEL
zerodbext.catalog-0.8.4.dist-info/metadata.json
zerodbext.catalog-0.8.4.dist-info/namespace_packages.txt
zerodbext.catalog-0.8.4.dist-info/top_level.txt
