Metadata-Version: 2.0
Name: zerodbext.catalog
Version: 0.8.4
Summary: Searching and indexing based on zope.index. Fork of repoze.catalog
Home-page: UNKNOWN
Author: ZeroDB
Author-email: UNKNOWN
License: BSD-derived (http://www.repoze.org/LICENSE.txt)
Keywords: indexing catalog search
Platform: UNKNOWN
Classifier: Intended Audience :: Developers
Classifier: Programming Language :: Python
Classifier: Programming Language :: Python :: 2
Classifier: Programming Language :: Python :: 2.6
Classifier: Programming Language :: Python :: 2.7
Classifier: Programming Language :: Python :: 3
Classifier: Programming Language :: Python :: 3.5
Classifier: Programming Language :: Python :: Implementation :: CPython
Classifier: Topic :: Internet :: WWW/HTTP :: Indexing/Search
Requires-Dist: ZODB
Requires-Dist: setuptools
Requires-Dist: six
Requires-Dist: zope.component
Requires-Dist: zope.index (>=3.5.0)
Provides-Extra: benchmark
Requires-Dist: PyChart; extra == 'benchmark'
Provides-Extra: docs
Requires-Dist: Sphinx; extra == 'docs'
Provides-Extra: testing
Requires-Dist: coverage; extra == 'testing'
Requires-Dist: nose; extra == 'testing'
